{
  "otaeguioihana_1": {
    "fid": 0,
    "keyId": 914,
    "name": "Otaegui, Oihana",
    "pre_name": "otaeguioihana",
    "inst": "Vicomtech, Parque Cient & Tecnol Gipuzkoa, Donostia San Sebastian 20009, Spain",
    "WOS": {
      "inst": "Vicomtech, Parque Cient & Tecnol Gipuzkoa, Donostia San Sebastian 20009, Spain",
      "A_id": [
        "ss9684069"
      ],
      "papers": [
        "6294af751649752aa187475a"
      ],
      "oriInst": "Vicomtech, Parque Cient & Tecnol Gipuzkoa, Donostia San Sebastian 20009, Spain"
    }
  },
  "otaeguioihana_0": {
    "fid": 0,
    "keyId": 914,
    "name": "Otaegui, Oihana",
    "pre_name": "otaeguioihana",
    "inst": "Basque Res & Technol Alliance BRTA, Vicomtech Fdn, Mikeletegi 57, San Sebastian 20009, Spain",
    "WOS": {
      "inst": "Basque Res & Technol Alliance BRTA, Vicomtech Fdn, Mikeletegi 57, San Sebastian 20009, Spain",
      "A_id": [
        "ss9683944"
      ],
      "papers": [
        "6294af751649752aa187472d"
      ],
      "oriInst": "Basque Res & Technol Alliance BRTA, Vicomtech Fdn, Mikeletegi 57, San Sebastian 20009, Spain"
    }
  },
  "khanshahzad_1": {
    "fid": 0,
    "keyId": 914,
    "name": "Khan, Shahzad",
    "pre_name": "khanshahzad",
    "inst": "Gnowit Inc, Kanata, ON K2W0B5, Canada",
    "WOS": {
      "inst": "Gnowit Inc, Kanata, ON K2W0B5, Canada",
      "A_id": [
        "ss9683970"
      ],
      "papers": [
        "6294af751649752aa1874735"
      ],
      "oriInst": "Gnowit Inc, Kanata, ON K2W0B5, Canada"
    }
  },
  "khanshahzad_0": {
    "fid": 0,
    "keyId": 914,
    "name": "Khan, Shahzad",
    "pre_name": "khanshahzad",
    "inst": "Gnowit Inc, 200-308 Legett Dr, Kanata, ON, Canada",
    "WOS": {
      "inst": "Gnowit Inc, 200-308 Legett Dr, Kanata, ON, Canada",
      "A_id": [
        "s9340436"
      ],
      "papers": [
        "6294af751649752aa1874747"
      ],
      "oriInst": "Gnowit Inc, 200-308 Legett Dr, Kanata, ON, Canada"
    }
  },
  "otaeguioihana_2": {
    "fid": 0,
    "keyId": 914,
    "name": "Otaegui, Oihana",
    "pre_name": "otaeguioihana",
    "inst": "Vicomtech Foundation Basque Research and Technology Alliance (BRTA) Mikeletegi 57 San Sebastian 20009 Spain",
    "SCOPUS": {
      "inst": "Vicomtech Foundation Basque Research and Technology Alliance (BRTA) Mikeletegi 57 San Sebastian 20009 Spain",
      "A_id": [
        "8638431600"
      ],
      "papers": [
        "6294af874c7cb9455f86d153",
        "6294af844c7cb9455f86d0ab"
      ],
      "oriInst": "Vicomtech Foundation Basque Research and Technology Alliance (BRTA) Mikeletegi 57 San Sebastian 20009 Spain"
    }
  },
  "naseeraisha_1": {
    "fid": 0,
    "keyId": 914,
    "name": "Naseer, Aisha",
    "pre_name": "naseeraisha",
    "inst": "Fujitsu Laboratories of Europe United Kingdom",
    "SCOPUS": {
      "inst": "Fujitsu Laboratories of Europe United Kingdom",
      "A_id": [
        "22635523000"
      ],
      "papers": [
        "6294af874c7cb9455f86d152"
      ],
      "oriInst": "Fujitsu Laboratories of Europe United Kingdom"
    }
  },
  "naseeraisha_0": {
    "fid": 0,
    "keyId": 914,
    "name": "Naseer, Aisha",
    "pre_name": "naseeraisha",
    "inst": "Fujitsu Labs Europe, Birmingham, W Midlands, England",
    "WOS": {
      "inst": "Fujitsu Labs Europe, Birmingham, W Midlands, England",
      "A_id": [
        "s8601866"
      ],
      "papers": [
        "6294af741649752aa187470a"
      ],
      "oriInst": "Fujitsu Labs Europe, Birmingham, W Midlands, England"
    }
  },
  "khanwasiq_1": {
    "fid": 0,
    "keyId": 914,
    "name": "Khan, Wasiq",
    "pre_name": "khanwasiq",
    "inst": "Faculty of Engineering and Technology Liverpool John Moores University Liverpool United Kingdom",
    "SCOPUS": {
      "inst": "Faculty of Engineering and Technology Liverpool John Moores University Liverpool United Kingdom",
      "A_id": [
        "55319932200"
      ],
      "papers": [
        "6294af874c7cb9455f86d151"
      ],
      "oriInst": "Faculty of Engineering and Technology Liverpool John Moores University Liverpool United Kingdom"
    }
  },
  "khanwasiq_0": {
    "fid": 0,
    "keyId": 914,
    "name": "Khan, Wasiq",
    "pre_name": "khanwasiq",
    "inst": "Liverpool John Moores Univ, Fac Engn & Technol, Liverpool L3 5UZ, Merseyside, England",
    "WOS": {
      "inst": "Liverpool John Moores Univ, Fac Engn & Technol, Liverpool L3 5UZ, Merseyside, England",
      "A_id": [
        "s8600615"
      ],
      "papers": [
        "6294af751649752aa187474d"
      ],
      "oriInst": "Liverpool John Moores Univ, Fac Engn & Technol, Liverpool L3 5UZ, Merseyside, England"
    }
  },
  "chengwenhuang_1": {
    "fid": 0,
    "keyId": 914,
    "name": "Cheng, Wen Huang",
    "pre_name": "chengwenhuang",
    "inst": "Department of Electronics Engineering National Chiao Tung University Hsinchu Taiwan",
    "SCOPUS": {
      "inst": "Department of Electronics Engineering National Chiao Tung University Hsinchu Taiwan",
      "A_id": [
        "24775341200"
      ],
      "papers": [
        "6294af854c7cb9455f86d0e6"
      ],
      "oriInst": "Department of Electronics Engineering National Chiao Tung University Hsinchu Taiwan"
    }
  },
  "chengwenhuang_0": {
    "fid": 0,
    "keyId": 914,
    "name": "Cheng, Wen-Huang",
    "pre_name": "chengwenhuang",
    "inst": "Natl Chiao Tung Univ, Inst Elect, Hsinchu, Taiwan",
    "WOS": {
      "inst": "Natl Chiao Tung Univ, Inst Elect, Hsinchu, Taiwan",
      "A_id": [
        "ss9683829"
      ],
      "papers": [
        "6294af741649752aa1874711"
      ],
      "oriInst": "Natl Chiao Tung Univ, Inst Elect, Hsinchu, Taiwan"
    }
  },
  "tanwarsudeep_1": {
    "fid": 0,
    "keyId": 914,
    "name": "Tanwar, Sudeep",
    "pre_name": "tanwarsudeep",
    "inst": "Department of Computer Science Engineering Institute of Technology Nirma University Ahmedabad 382481 India",
    "SCOPUS": {
      "inst": "Department of Computer Science Engineering Institute of Technology Nirma University Ahmedabad 382481 India",
      "A_id": [
        "56576145100"
      ],
      "papers": [
        "6294af854c7cb9455f86d0e7"
      ],
      "oriInst": "Department of Computer Science Engineering Institute of Technology Nirma University Ahmedabad 382481 India"
    }
  },
  "tanwarsudeep_0": {
    "fid": 0,
    "keyId": 914,
    "name": "Tanwar, Sudeep",
    "pre_name": "tanwarsudeep",
    "inst": "Nirma Univ, Inst Technol, Dept Comp Sci Engn, Ahmadabad 382481, Gujarat, India",
    "WOS": {
      "inst": "Nirma Univ, Inst Technol, Dept Comp Sci Engn, Ahmadabad 382481, Gujarat, India",
      "A_id": [
        "ss9683837"
      ],
      "papers": [
        "6294af741649752aa1874714"
      ],
      "oriInst": "Nirma Univ, Inst Technol, Dept Comp Sci Engn, Ahmadabad 382481, Gujarat, India"
    }
  },
  "parkkangryoung_1": {
    "fid": 0,
    "keyId": 914,
    "name": "Park, Kang-ryoung",
    "pre_name": "parkkangryoung",
    "inst": "Division of Electronics and Electrical Engineering Dongguk University Seoul 04620 South Korea",
    "SCOPUS": {
      "inst": "Division of Electronics and Electrical Engineering Dongguk University Seoul 04620 South Korea",
      "A_id": [
        "8983316300"
      ],
      "papers": [
        "6294af874c7cb9455f86d150"
      ],
      "oriInst": "Division of Electronics and Electrical Engineering Dongguk University Seoul 04620 South Korea"
    }
  },
  "parkkangryoung_0": {
    "fid": 0,
    "keyId": 914,
    "name": "Park, Kang Ryoung",
    "pre_name": "parkkangryoung",
    "inst": "Dongguk Univ, Div Elect & Elect Engn, Seoul 04620, South Korea",
    "WOS": {
      "inst": "Dongguk Univ, Div Elect & Elect Engn, Seoul 04620, South Korea",
      "A_id": [
        "s1289666"
      ],
      "papers": [
        "6294af751649752aa187477a"
      ],
      "oriInst": "Dongguk Univ, Div Elect & Elect Engn, Seoul 04620, South Korea"
    }
  },
  "lili_1": {
    "fid": 0,
    "keyId": 914,
    "name": "Li, Li",
    "pre_name": "lili",
    "inst": "Department of Automation BNRist Tsinghua University Beijing 100084 China",
    "SCOPUS": {
      "inst": "Department of Automation BNRist Tsinghua University Beijing 100084 China",
      "A_id": [
        "56183602800"
      ],
      "papers": [
        "6294af834c7cb9455f86d053"
      ],
      "oriInst": "Department of Automation BNRist Tsinghua University Beijing 100084 China"
    }
  },
  "lili_0": {
    "fid": 0,
    "keyId": 914,
    "name": "Li, Li",
    "pre_name": "lili",
    "inst": "Tsinghua Univ, Dept Automat, BNRist, Beijing 100084, Peoples R China",
    "WOS": {
      "inst": "Tsinghua Univ, Dept Automat, BNRist, Beijing 100084, Peoples R China",
      "A_id": [
        "s2161629"
      ],
      "papers": [
        "6294af751649752aa1874757"
      ],
      "oriInst": "Tsinghua Univ, Dept Automat, BNRist, Beijing 100084, Peoples R China"
    }
  },
  "merzoukirochdi_1": {
    "fid": 0,
    "keyId": 914,
    "name": "Merzouki, Rochdi",
    "pre_name": "merzoukirochdi",
    "inst": "Laboratory Centre de Recherche en Informatique Signal et Automatique de Lille (CRIStAL) Polytech Lille University of Lille Lille 59655 France",
    "SCOPUS": {
      "inst": "Laboratory Centre de Recherche en Informatique Signal et Automatique de Lille (CRIStAL) Polytech Lille University of Lille Lille 59655 France",
      "A_id": [
        "15840190400"
      ],
      "papers": [
        "6294af854c7cb9455f86d0ea"
      ],
      "oriInst": "Laboratory Centre de Recherche en Informatique Signal et Automatique de Lille (CRIStAL) Polytech Lille University of Lille Lille 59655 France"
    }
  },
  "merzoukirochdi_0": {
    "fid": 0,
    "keyId": 914,
    "name": "Merzouki, Rochdi",
    "pre_name": "merzoukirochdi",
    "inst": "Ecole Mil Polytech, Dept Mech Engn, Algiers 16111, Algeria",
    "WOS": {
      "inst": "Ecole Mil Polytech, Dept Mech Engn, Algiers 16111, Algeria",
      "A_id": [
        "s8077929"
      ],
      "papers": [
        "6294af751649752aa1874753"
      ],
      "oriInst": "Ecole Mil Polytech, Dept Mech Engn, Algiers 16111, Algeria"
    }
  },
  "huangkaibin_1": {
    "fid": 0,
    "keyId": 914,
    "name": "Huang, Kaibin",
    "pre_name": "huangkaibin",
    "inst": "Department of Electrical and Electronic Engineering University of Hong Kong Hong Kong",
    "SCOPUS": {
      "inst": "Department of Electrical and Electronic Engineering University of Hong Kong Hong Kong",
      "A_id": [
        "15834779200"
      ],
      "papers": [
        "6294af874c7cb9455f86d14e"
      ],
      "oriInst": "Department of Electrical and Electronic Engineering University of Hong Kong Hong Kong"
    }
  },
  "huangkaibin_0": {
    "fid": 0,
    "keyId": 914,
    "name": "Huang, Kaibin",
    "pre_name": "huangkaibin",
    "inst": "South China Univ Technol, Sch Elect & Informat Engn, Guangzhou 510641, Peoples R China",
    "WOS": {
      "inst": "South China Univ Technol, Sch Elect & Informat Engn, Guangzhou 510641, Peoples R China",
      "A_id": [
        "ss9684119"
      ],
      "papers": [
        "6294af751649752aa1874769"
      ],
      "oriInst": "South China Univ Technol, Sch Elect & Informat Engn, Guangzhou 510641, Peoples R China"
    }
  },
  "shimdavidhyunchul_1": {
    "fid": 0,
    "keyId": 914,
    "name": "Shim, David Hyunchul",
    "pre_name": "shimdavidhyunchul",
    "inst": "School of Electrical Engineering Korea Advanced Institute of Science and Technology Daejeon South Korea",
    "SCOPUS": {
      "inst": "School of Electrical Engineering Korea Advanced Institute of Science and Technology Daejeon South Korea",
      "A_id": [
        "35231144100"
      ],
      "papers": [
        "6294af854c7cb9455f86d0de"
      ],
      "oriInst": "School of Electrical Engineering Korea Advanced Institute of Science and Technology Daejeon South Korea"
    }
  },
  "shimdavidhyunchul_0": {
    "fid": 0,
    "keyId": 914,
    "name": "Shim, David Hyunchul",
    "pre_name": "shimdavidhyunchul",
    "inst": "Korea Adv Inst Sci & Technol, Sch Elect Engn, KS015, Daejeon, South Korea",
    "WOS": {
      "inst": "Korea Adv Inst Sci & Technol, Sch Elect Engn, KS015, Daejeon, South Korea",
      "A_id": [
        "s8595304"
      ],
      "papers": [
        "6294af741649752aa1874713"
      ],
      "oriInst": "Korea Adv Inst Sci & Technol, Sch Elect Engn, KS015, Daejeon, South Korea"
    }
  },
  "shirongye_1": {
    "fid": 0,
    "keyId": 914,
    "name": "Shi, Rongye",
    "pre_name": "shirongye",
    "inst": "Department of Civil Engineering and Engineering Mechanics Columbia University United States",
    "SCOPUS": {
      "inst": "Department of Civil Engineering and Engineering Mechanics Columbia University United States",
      "A_id": [
        "57190345282"
      ],
      "papers": [
        "6294af854c7cb9455f86d0dd"
      ],
      "oriInst": "Department of Civil Engineering and Engineering Mechanics Columbia University United States"
    }
  },
  "shirongye_0": {
    "fid": 0,
    "keyId": 914,
    "name": "Shi, Rongye",
    "pre_name": "shirongye",
    "inst": "Columbia Univ, Dept Civil Engn & Engn Mech, New York, NY 10027 USA",
    "WOS": {
      "inst": "Columbia Univ, Dept Civil Engn & Engn Mech, New York, NY 10027 USA",
      "A_id": [
        "s8595063"
      ],
      "papers": [
        "6294af741649752aa18746f0"
      ],
      "oriInst": "Columbia Univ, Dept Civil Engn & Engn Mech, New York, NY 10027 USA"
    }
  },
  "maynardkasia_1": {
    "fid": 0,
    "keyId": 914,
    "name": "Maynard, Kasia",
    "pre_name": "maynardkasia",
    "inst": "WORKTECH Academy Kingston upon Thames United Kingdom Department of Urban Studies and Planning University of Sheffield Sheffield United Kingdom",
    "SCOPUS": {
      "inst": "WORKTECH Academy Kingston upon Thames United Kingdom Department of Urban Studies and Planning University of Sheffield Sheffield United Kingdom",
      "A_id": [
        "57222387128"
      ],
      "papers": [
        "6294af874c7cb9455f86d14a"
      ],
      "oriInst": "WORKTECH Academy Kingston upon Thames United Kingdom Department of Urban Studies and Planning University of Sheffield Sheffield United Kingdom"
    }
  },
  "maynardkasia_0": {
    "fid": 0,
    "keyId": 914,
    "name": "Maynard, Kasia",
    "pre_name": "maynardkasia",
    "inst": "WORKTECH Acad, Kingston Upon Thames, Surrey, England",
    "WOS": {
      "inst": "WORKTECH Acad, Kingston Upon Thames, Surrey, England",
      "A_id": [
        "ss9683984"
      ],
      "papers": [
        "6294af751649752aa187473b"
      ],
      "oriInst": "WORKTECH Acad, Kingston Upon Thames, Surrey, England"
    }
  },
  "klumppmatthias_1": {
    "fid": 0,
    "keyId": 914,
    "name": "Klumpp, Matthias",
    "pre_name": "klumppmatthias",
    "inst": "Institute for Logistics and Service Management FOM University of Applied Sciences Essen Germany Chair for Production and Logistics Faculty of Business and Economics Georg-August-University of Göttingen Göttingen Germany Fraunhofer IML Dortmund Germany",
    "SCOPUS": {
      "inst": "Institute for Logistics and Service Management FOM University of Applied Sciences Essen Germany Chair for Production and Logistics Faculty of Business and Economics Georg-August-University of Göttingen Göttingen Germany Fraunhofer IML Dortmund Germany",
      "A_id": [
        "37087477300"
      ],
      "papers": [
        "6294af874c7cb9455f86d149"
      ],
      "oriInst": "Institute for Logistics and Service Management FOM University of Applied Sciences Essen Germany Chair for Production and Logistics Faculty of Business and Economics Georg-August-University of Göttingen Göttingen Germany Fraunhofer IML Dortmund Germany"
    }
  },
  "klumppmatthias_0": {
    "fid": 0,
    "keyId": 914,
    "name": "Klumpp, Matthias",
    "pre_name": "klumppmatthias",
    "inst": "FOM Univ Appl Sci, Inst Logist & Serv Management, Essen, Germany",
    "WOS": {
      "inst": "FOM Univ Appl Sci, Inst Logist & Serv Management, Essen, Germany",
      "A_id": [
        "s5313960"
      ],
      "papers": [
        "6294af751649752aa1874745"
      ],
      "oriInst": "FOM Univ Appl Sci, Inst Logist & Serv Management, Essen, Germany"
    }
  },
  "wangfan_1": {
    "fid": 0,
    "keyId": 914,
    "name": "Wang, Fan",
    "pre_name": "wangfan",
    "inst": "SF Motors Inc SF Motors Inc Santa Clara California United States (e-mail: fan.wang@driveseres.com)",
    "SCOPUS": {
      "inst": "SF Motors Inc SF Motors Inc Santa Clara California United States (e-mail: fan.wang@driveseres.com)",
      "A_id": [
        "57219732632"
      ],
      "papers": [
        "6294af864c7cb9455f86d144"
      ],
      "oriInst": "SF Motors Inc SF Motors Inc Santa Clara California United States (e-mail: fan.wang@driveseres.com)"
    }
  },
  "wangfan_0": {
    "fid": 0,
    "keyId": 914,
    "name": "Wang, Fan",
    "pre_name": "wangfan",
    "inst": "Seres Inc, Santa Clara, CA 95054 USA",
    "WOS": {
      "inst": "Seres Inc, Santa Clara, CA 95054 USA",
      "A_id": [
        "ss9684112"
      ],
      "papers": [
        "6294af751649752aa1874765"
      ],
      "oriInst": "Seres Inc, Santa Clara, CA 95054 USA"
    }
  },
  "abdelgawadhossam_1": {
    "fid": 0,
    "keyId": 914,
    "name": "Abdelgawad, Hossam",
    "pre_name": "abdelgawadhossam",
    "inst": "Traffic and Highway Engineering Department Cairo University Cairo 12613 Egypt",
    "SCOPUS": {
      "inst": "Traffic and Highway Engineering Department Cairo University Cairo 12613 Egypt",
      "A_id": [
        "36975053100"
      ],
      "papers": [
        "6294af854c7cb9455f86d0d9"
      ],
      "oriInst": "Traffic and Highway Engineering Department Cairo University Cairo 12613 Egypt"
    }
  },
  "abdelgawadhossam_0": {
    "fid": 0,
    "keyId": 914,
    "name": "Abdelgawad, Hossam",
    "pre_name": "abdelgawadhossam",
    "inst": "Cairo Univ, Traff & Highway Engn Dept, Cairo 12613, Egypt",
    "WOS": {
      "inst": "Cairo Univ, Traff & Highway Engn Dept, Cairo 12613, Egypt",
      "A_id": [
        "ss9684043"
      ],
      "papers": [
        "6294af751649752aa1874752"
      ],
      "oriInst": "Cairo Univ, Traff & Highway Engn Dept, Cairo 12613, Egypt"
    }
  },
  "mahmoodarif_1": {
    "fid": 0,
    "keyId": 914,
    "name": "Mahmood, Arif",
    "pre_name": "mahmoodarif",
    "inst": "Department of Computer Science Information Technology University Lahore Pakistan",
    "SCOPUS": {
      "inst": "Department of Computer Science Information Technology University Lahore Pakistan",
      "A_id": [
        "55636036300"
      ],
      "papers": [
        "6294af844c7cb9455f86d0a3"
      ],
      "oriInst": "Department of Computer Science Information Technology University Lahore Pakistan"
    }
  },
  "mahmoodarif_0": {
    "fid": 0,
    "keyId": 914,
    "name": "Mahmood, Arif",
    "pre_name": "mahmoodarif",
    "inst": "Informat Technol Univ, Dept Comp Sci, Lahore, Pakistan",
    "WOS": {
      "inst": "Informat Technol Univ, Dept Comp Sci, Lahore, Pakistan",
      "A_id": [
        "s22214"
      ],
      "papers": [
        "6294af741649752aa1874724"
      ],
      "oriInst": "Informat Technol Univ, Dept Comp Sci, Lahore, Pakistan"
    }
  },
  "sunyongbin_1": {
    "fid": 0,
    "keyId": 914,
    "name": "Sun, Yongbin",
    "pre_name": "sunyongbin",
    "inst": "Department of Mechanical Engineering Massachusetts Institute of Technology Cambridge MA  02139 United States",
    "SCOPUS": {
      "inst": "Department of Mechanical Engineering Massachusetts Institute of Technology Cambridge MA  02139 United States",
      "A_id": [
        "57202455124"
      ],
      "papers": [
        "6294af854c7cb9455f86d0d3"
      ],
      "oriInst": "Department of Mechanical Engineering Massachusetts Institute of Technology Cambridge MA  02139 United States"
    }
  },
  "sunyongbin_0": {
    "fid": 0,
    "keyId": 914,
    "name": "Sun, Yongbin",
    "pre_name": "sunyongbin",
    "inst": "MIT, Dept Mech Engn, 77 Massachusetts Ave, Cambridge, MA 02139 USA",
    "WOS": {
      "inst": "MIT, Dept Mech Engn, 77 Massachusetts Ave, Cambridge, MA 02139 USA",
      "A_id": [
        "ss9683911"
      ],
      "papers": [
        "6294af741649752aa1874726"
      ],
      "oriInst": "MIT, Dept Mech Engn, 77 Massachusetts Ave, Cambridge, MA 02139 USA"
    }
  },
  "lijonathan_1": {
    "fid": 0,
    "keyId": 914,
    "name": "Li, Jonathan",
    "pre_name": "lijonathan",
    "inst": "University of Waterloo Waterloo N2L 3G1 Canada",
    "SCOPUS": {
      "inst": "University of Waterloo Waterloo N2L 3G1 Canada",
      "A_id": [
        "57235557700"
      ],
      "papers": [
        "6294af844c7cb9455f86d0cd"
      ],
      "oriInst": "University of Waterloo Waterloo N2L 3G1 Canada"
    }
  },
  "lijonathan_0": {
    "fid": 0,
    "keyId": 914,
    "name": "Li, Jonathan",
    "pre_name": "lijonathan",
    "inst": "Univ Fed Mato Grosso do Sul, BR-79070900 Campo Grande, MS, Brazil",
    "WOS": {
      "inst": "Univ Fed Mato Grosso do Sul, BR-79070900 Campo Grande, MS, Brazil",
      "A_id": [
        "ss9684135"
      ],
      "papers": [
        "6294af751649752aa1874770"
      ],
      "oriInst": "Univ Fed Mato Grosso do Sul, BR-79070900 Campo Grande, MS, Brazil"
    }
  },
  "paugiovanni_1": {
    "fid": 0,
    "keyId": 914,
    "name": "Pau, Giovanni",
    "pre_name": "paugiovanni",
    "inst": "Faculty of Engineering and Architecture Kore University of Enna Enna 94100 Italy",
    "SCOPUS": {
      "inst": "Faculty of Engineering and Architecture Kore University of Enna Enna 94100 Italy",
      "A_id": [
        "57201304014"
      ],
      "papers": [
        "6294af854c7cb9455f86d0d8"
      ],
      "oriInst": "Faculty of Engineering and Architecture Kore University of Enna Enna 94100 Italy"
    }
  },
  "paugiovanni_0": {
    "fid": 0,
    "keyId": 914,
    "name": "Pau, Giovanni",
    "pre_name": "paugiovanni",
    "inst": "Kore Univ Enna, Fac Engn & Architecture, I-94100 Enna, Italy",
    "WOS": {
      "inst": "Kore Univ Enna, Fac Engn & Architecture, I-94100 Enna, Italy",
      "A_id": [
        "s5648"
      ],
      "papers": [
        "6294af741649752aa187472b"
      ],
      "oriInst": "Kore Univ Enna, Fac Engn & Architecture, I-94100 Enna, Italy"
    }
  },
  "shifeifei_1": {
    "fid": 0,
    "keyId": 914,
    "name": "Shi, Feifei",
    "pre_name": "shifeifei",
    "inst": "School of Computer and Communication Engineering University of Science and Technology Beijing Beijing 100083 China.",
    "SCOPUS": {
      "inst": "School of Computer and Communication Engineering University of Science and Technology Beijing Beijing 100083 China.",
      "A_id": [
        "57200331831"
      ],
      "papers": [
        "6294af864c7cb9455f86d141"
      ],
      "oriInst": "School of Computer and Communication Engineering University of Science and Technology Beijing Beijing 100083 China."
    }
  },
  "shifeifei_0": {
    "fid": 0,
    "keyId": 914,
    "name": "Shi, Feifei",
    "pre_name": "shifeifei",
    "inst": "Natl Univ Modern Languages, Dept Comp Sci, Islamabad 44000, Pakistan",
    "WOS": {
      "inst": "Natl Univ Modern Languages, Dept Comp Sci, Islamabad 44000, Pakistan",
      "A_id": [
        "ss9683738"
      ],
      "papers": [
        "6294af741649752aa18746e7"
      ],
      "oriInst": "Natl Univ Modern Languages, Dept Comp Sci, Islamabad 44000, Pakistan"
    }
  },
  "tonellapaolo_1": {
    "fid": 0,
    "keyId": 914,
    "name": "Tonella, Paolo",
    "pre_name": "tonellapaolo",
    "inst": "Software Institute - Università della Svizzera Italiana Lugano Switzerland",
    "SCOPUS": {
      "inst": "Software Institute - Università della Svizzera Italiana Lugano Switzerland",
      "A_id": [
        "7003489194"
      ],
      "papers": [
        "6294af854c7cb9455f86d0dc",
        "6294af864c7cb9455f86d129"
      ],
      "oriInst": "Software Institute - Università della Svizzera Italiana Lugano Switzerland"
    }
  },
  "tonellapaolo_0": {
    "fid": 0,
    "keyId": 914,
    "name": "Tonella, Paolo",
    "pre_name": "tonellapaolo",
    "inst": "USI, Software Inst, Lugano, Switzerland",
    "WOS": {
      "inst": "USI, Software Inst, Lugano, Switzerland",
      "A_id": [
        "ss9683814"
      ],
      "papers": [
        "6294af741649752aa1874708"
      ],
      "oriInst": "USI, Software Inst, Lugano, Switzerland"
    }
  },
  "kitanohiroaki_1": {
    "fid": 0,
    "keyId": 914,
    "name": "Kitano, Hiroaki",
    "pre_name": "kitanohiroaki",
    "inst": "The Systems Biology Institute Tokyo Japan Okinawa Institute of Science and Technology Graduate School Okinawa Japan Sony Computer Science Laboratories Inc. Tokyo Japan Sony AI Inc. Tokyo Japan The Alan Turing Institute London United Kingdom",
    "SCOPUS": {
      "inst": "The Systems Biology Institute Tokyo Japan Okinawa Institute of Science and Technology Graduate School Okinawa Japan Sony Computer Science Laboratories Inc. Tokyo Japan Sony AI Inc. Tokyo Japan The Alan Turing Institute London United Kingdom",
      "A_id": [
        "57214731781"
      ],
      "papers": [
        "6294af844c7cb9455f86d093"
      ],
      "oriInst": "The Systems Biology Institute Tokyo Japan Okinawa Institute of Science and Technology Graduate School Okinawa Japan Sony Computer Science Laboratories Inc. Tokyo Japan Sony AI Inc. Tokyo Japan The Alan Turing Institute London United Kingdom"
    }
  },
  "kitanohiroaki_0": {
    "fid": 0,
    "keyId": 914,
    "name": "Kitano, Hiroaki",
    "pre_name": "kitanohiroaki",
    "inst": "Syst Biol Inst, Tokyo, Japan",
    "WOS": {
      "inst": "Syst Biol Inst, Tokyo, Japan",
      "A_id": [
        "s5582915"
      ],
      "papers": [
        "6294af751649752aa187473a"
      ],
      "oriInst": "Syst Biol Inst, Tokyo, Japan"
    }
  },
  "zhangjuan_1": {
    "fid": 0,
    "keyId": 914,
    "name": "Zhang, Juan",
    "pre_name": "zhangjuan",
    "inst": "College of Engineering Mathematics and Physical Sciences University of Exeter Exeter EX4 4QF United Kingdom",
    "SCOPUS": {
      "inst": "College of Engineering Mathematics and Physical Sciences University of Exeter Exeter EX4 4QF United Kingdom",
      "A_id": [
        "57217685849"
      ],
      "papers": [
        "6294af844c7cb9455f86d0ca"
      ],
      "oriInst": "College of Engineering Mathematics and Physical Sciences University of Exeter Exeter EX4 4QF United Kingdom"
    }
  },
  "zhangjuan_0": {
    "fid": 0,
    "keyId": 914,
    "name": "Zhang, Juan",
    "pre_name": "zhangjuan",
    "inst": "Univ Exeter, Coll Engn Math & Phys Sci, Exeter EX4 4QF, Devon, England",
    "WOS": {
      "inst": "Univ Exeter, Coll Engn Math & Phys Sci, Exeter EX4 4QF, Devon, England",
      "A_id": [
        "s7290865"
      ],
      "papers": [
        "6294af741649752aa187471e"
      ],
      "oriInst": "Univ Exeter, Coll Engn Math & Phys Sci, Exeter EX4 4QF, Devon, England"
    }
  },
  "alturjmanfadi_1": {
    "fid": 0,
    "keyId": 914,
    "name": "Al-Turjman, Fadi",
    "pre_name": "alturjmanfadi",
    "inst": "Department of Artificial Intelligence Engineering Research Centre for AI and IoT Near East University Nicosia Mersin 10 Turkey",
    "SCOPUS": {
      "inst": "Department of Artificial Intelligence Engineering Research Centre for AI and IoT Near East University Nicosia Mersin 10 Turkey",
      "A_id": [
        "20336944100"
      ],
      "papers": [
        "6294af844c7cb9455f86d0ac"
      ],
      "oriInst": "Department of Artificial Intelligence Engineering Research Centre for AI and IoT Near East University Nicosia Mersin 10 Turkey"
    }
  },
  "alturjmanfadi_0": {
    "fid": 0,
    "keyId": 914,
    "name": "Al-Turjman, Fadi",
    "pre_name": "alturjmanfadi",
    "inst": "Near East Univ, Res Ctr AI & IoT, Dept Artificial Intelligence Engn, Mersin 10, Nicosia, Turkey",
    "WOS": {
      "inst": "Near East Univ, Res Ctr AI & IoT, Dept Artificial Intelligence Engn, Mersin 10, Nicosia, Turkey",
      "A_id": [
        "ss9683803"
      ],
      "papers": [
        "6294af741649752aa1874702"
      ],
      "oriInst": "Near East Univ, Res Ctr AI & IoT, Dept Artificial Intelligence Engn, Mersin 10, Nicosia, Turkey"
    }
  },
  "hayoungguk_1": {
    "fid": 0,
    "keyId": 914,
    "name": "Ha, Youngguk",
    "pre_name": "hayoungguk",
    "inst": "Konkuk University Seoul South Korea",
    "SCOPUS": {
      "inst": "Konkuk University Seoul South Korea",
      "A_id": [
        "23389377100"
      ],
      "papers": [
        "6294af834c7cb9455f86d061"
      ],
      "oriInst": "Konkuk University Seoul South Korea"
    }
  },
  "hayoungguk_0": {
    "fid": 0,
    "keyId": 914,
    "name": "Ha, Young-guk",
    "pre_name": "hayoungguk",
    "inst": "Konkuk Univ, Seoul, South Korea",
    "WOS": {
      "inst": "Konkuk Univ, Seoul, South Korea",
      "A_id": [
        "ss9466149"
      ],
      "papers": [
        "6294af741649752aa18746e9"
      ],
      "oriInst": "Konkuk Univ, Seoul, South Korea"
    }
  },
  "zhangyao_1": {
    "fid": 0,
    "keyId": 914,
    "name": "Zhang, Yao",
    "pre_name": "zhangyao",
    "inst": "State Key Laboratory of Integrated Services Networks Xidian University Xi'an 710071 China and also with the Research Institute of Smart Transportation Xidian University Xi'an 710071 China.",
    "SCOPUS": {
      "inst": "State Key Laboratory of Integrated Services Networks Xidian University Xi'an 710071 China and also with the Research Institute of Smart Transportation Xidian University Xi'an 710071 China.",
      "A_id": [
        "57194837082"
      ],
      "papers": [
        "6294af864c7cb9455f86d13d"
      ],
      "oriInst": "State Key Laboratory of Integrated Services Networks Xidian University Xi'an 710071 China and also with the Research Institute of Smart Transportation Xidian University Xi'an 710071 China."
    }
  },
  "zhangyao_0": {
    "fid": 0,
    "keyId": 914,
    "name": "Zhang, Yao",
    "pre_name": "zhangyao",
    "inst": "Xidian Univ, Sch Cyber Engn, Xian 710071, Peoples R China",
    "WOS": {
      "inst": "Xidian Univ, Sch Cyber Engn, Xian 710071, Peoples R China",
      "A_id": [
        "s1622303"
      ],
      "papers": [
        "6294af741649752aa18746f1"
      ],
      "oriInst": "Xidian Univ, Sch Cyber Engn, Xian 710071, Peoples R China"
    }
  },
  "vasudevanramak_1": {
    "fid": 0,
    "keyId": 914,
    "name": "Vasudevan, Rama K.",
    "pre_name": "vasudevanramak",
    "inst": "Center for Nanophase Materials Sciences Oak Ridge National Laboratory Oak Ridge TN  37831 United States",
    "SCOPUS": {
      "inst": "Center for Nanophase Materials Sciences Oak Ridge National Laboratory Oak Ridge TN  37831 United States",
      "A_id": [
        "57203197820"
      ],
      "papers": [
        "6294af844c7cb9455f86d0af"
      ],
      "oriInst": "Center for Nanophase Materials Sciences Oak Ridge National Laboratory Oak Ridge TN  37831 United States"
    }
  },
  "vasudevanramak_0": {
    "fid": 0,
    "keyId": 914,
    "name": "Vasudevan, Rama K.",
    "pre_name": "vasudevanramak",
    "inst": "Oak Ridge Natl Lab, Computat Sci & Engn Div, Oak Ridge, TN 37831 USA",
    "WOS": {
      "inst": "Oak Ridge Natl Lab, Computat Sci & Engn Div, Oak Ridge, TN 37831 USA",
      "A_id": [
        "ss9683810"
      ],
      "papers": [
        "6294af741649752aa1874706"
      ],
      "oriInst": "Oak Ridge Natl Lab, Computat Sci & Engn Div, Oak Ridge, TN 37831 USA"
    }
  },
  "meinertedward_1": {
    "fid": 0,
    "keyId": 914,
    "name": "Meinert, Edward",
    "pre_name": "meinertedward",
    "inst": "Centre for Health Technology University of Plymouth Plymouth United Kingdom Department of Primary Care and Public Health Imperial College London London United Kingdom",
    "SCOPUS": {
      "inst": "Centre for Health Technology University of Plymouth Plymouth United Kingdom Department of Primary Care and Public Health Imperial College London London United Kingdom",
      "A_id": [
        "57202516550"
      ],
      "papers": [
        "6294af844c7cb9455f86d0c5"
      ],
      "oriInst": "Centre for Health Technology University of Plymouth Plymouth United Kingdom Department of Primary Care and Public Health Imperial College London London United Kingdom"
    }
  },
  "meinertedward_0": {
    "fid": 0,
    "keyId": 914,
    "name": "Meinert, Edward",
    "pre_name": "meinertedward",
    "inst": "Univ Oxford, Oxford, England",
    "WOS": {
      "inst": "Univ Oxford, Oxford, England",
      "A_id": [
        "ss9684033"
      ],
      "papers": [
        "6294af751649752aa187474e"
      ],
      "oriInst": "Univ Oxford, Oxford, England"
    }
  },
  "sadikmohamed_1": {
    "fid": 0,
    "keyId": 914,
    "name": "Sadik, Mohamed",
    "pre_name": "sadikmohamed",
    "inst": "Wireless@VT Blacksburg VA 24061 USA and also with the Department of Electrical and Computer Engineering Virginia Tech Blacksburg VA 24061 USA.",
    "SCOPUS": {
      "inst": "Wireless@VT Blacksburg VA 24061 USA and also with the Department of Electrical and Computer Engineering Virginia Tech Blacksburg VA 24061 USA.",
      "A_id": [
        "35269781800"
      ],
      "papers": [
        "6294af864c7cb9455f86d136"
      ],
      "oriInst": "Wireless@VT Blacksburg VA 24061 USA and also with the Department of Electrical and Computer Engineering Virginia Tech Blacksburg VA 24061 USA."
    }
  },
  "sadikmohamed_0": {
    "fid": 0,
    "keyId": 914,
    "name": "Sadik, Mohamed",
    "pre_name": "sadikmohamed",
    "inst": "Wireless VT, Blacksburg, VA 24061 USA",
    "WOS": {
      "inst": "Wireless VT, Blacksburg, VA 24061 USA",
      "A_id": [
        "ss9684048"
      ],
      "papers": [
        "6294af751649752aa1874754"
      ],
      "oriInst": "Wireless VT, Blacksburg, VA 24061 USA"
    }
  },
  "cedergerbrand_1": {
    "fid": 0,
    "keyId": 914,
    "name": "Ceder, Gerbrand",
    "pre_name": "cedergerbrand",
    "inst": "Department of Materials Science and Engineering UC Berkeley Berkeley CA  94720 United States Materials Sciences Division Lawrence Berkeley National Laboratory Berkeley CA  94720 United States",
    "SCOPUS": {
      "inst": "Department of Materials Science and Engineering UC Berkeley Berkeley CA  94720 United States Materials Sciences Division Lawrence Berkeley National Laboratory Berkeley CA  94720 United States",
      "A_id": [
        "7006338051"
      ],
      "papers": [
        "6294af844c7cb9455f86d0bf"
      ],
      "oriInst": "Department of Materials Science and Engineering UC Berkeley Berkeley CA  94720 United States Materials Sciences Division Lawrence Berkeley National Laboratory Berkeley CA  94720 United States"
    }
  },
  "cedergerbrand_0": {
    "fid": 0,
    "keyId": 914,
    "name": "Ceder, Gerbrand",
    "pre_name": "cedergerbrand",
    "inst": "Lawrence Berkeley Natl Lab, Mat Sci Div, Berkeley, CA 94720 USA",
    "WOS": {
      "inst": "Lawrence Berkeley Natl Lab, Mat Sci Div, Berkeley, CA 94720 USA",
      "A_id": [
        "s8208422"
      ],
      "papers": [
        "6294af741649752aa187470c"
      ],
      "oriInst": "Lawrence Berkeley Natl Lab, Mat Sci Div, Berkeley, CA 94720 USA"
    }
  },
  "vanderaalstwilmp_1": {
    "fid": 0,
    "keyId": 914,
    "name": "van der Aalst, Wil M.P.",
    "pre_name": "vanderaalstwilmp",
    "inst": "RWTH Aachen University Fraunhofer Institut für Angewandte Informationstechnik Ahornstr. 55 Aachen D-52074 Germany",
    "SCOPUS": {
      "inst": "RWTH Aachen University Fraunhofer Institut für Angewandte Informationstechnik Ahornstr. 55 Aachen D-52074 Germany",
      "A_id": [
        "7007153024"
      ],
      "papers": [
        "6294af864c7cb9455f86d132"
      ],
      "oriInst": "RWTH Aachen University Fraunhofer Institut für Angewandte Informationstechnik Ahornstr. 55 Aachen D-52074 Germany"
    }
  },
  "vanderaalstwilmp_0": {
    "fid": 0,
    "keyId": 914,
    "name": "van der Aalst, Wil M. P.",
    "pre_name": "vanderaalstwilmp",
    "inst": "Rhein Westfal TH Aachen, Fraunhofer Inst Angew Informat Tech, Ahornstr 55, D-52074 Aachen, Germany",
    "WOS": {
      "inst": "Rhein Westfal TH Aachen, Fraunhofer Inst Angew Informat Tech, Ahornstr 55, D-52074 Aachen, Germany",
      "A_id": [
        "s9319832"
      ],
      "papers": [
        "6294af751649752aa1874767"
      ],
      "oriInst": "Rhein Westfal TH Aachen, Fraunhofer Inst Angew Informat Tech, Ahornstr 55, D-52074 Aachen, Germany"
    }
  },
  "dengxinwei_1": {
    "fid": 0,
    "keyId": 914,
    "name": "Deng, Xinwei",
    "pre_name": "dengxinwei",
    "inst": "Department of Statistics Virginia Tech Blacksburg VA United States",
    "SCOPUS": {
      "inst": "Department of Statistics Virginia Tech Blacksburg VA United States",
      "A_id": [
        "55548133200"
      ],
      "papers": [
        "6294af864c7cb9455f86d131"
      ],
      "oriInst": "Department of Statistics Virginia Tech Blacksburg VA United States"
    }
  },
  "dengxinwei_0": {
    "fid": 0,
    "keyId": 914,
    "name": "Deng, Xinwei",
    "pre_name": "dengxinwei",
    "inst": "Virginia Tech, Dept Stat, Blacksburg, VA 24061 USA",
    "WOS": {
      "inst": "Virginia Tech, Dept Stat, Blacksburg, VA 24061 USA",
      "A_id": [
        "s2219324"
      ],
      "papers": [
        "6294af741649752aa1874710"
      ],
      "oriInst": "Virginia Tech, Dept Stat, Blacksburg, VA 24061 USA"
    }
  },
  "kimyoungseop_1": {
    "fid": 0,
    "keyId": 914,
    "name": "Kim, Youngseop",
    "pre_name": "kimyoungseop",
    "inst": "Electronic and Electrical Engineerin Dankook University 152 Jukjeon-ro Suji-gu Gyeonggi-do Yongin-si 16890 South Korea",
    "SCOPUS": {
      "inst": "Electronic and Electrical Engineerin Dankook University 152 Jukjeon-ro Suji-gu Gyeonggi-do Yongin-si 16890 South Korea",
      "A_id": [
        "55656076200"
      ],
      "papers": [
        "6294af844c7cb9455f86d0ae",
        "6294af854c7cb9455f86d103"
      ],
      "oriInst": "Electronic and Electrical Engineerin Dankook University 152 Jukjeon-ro Suji-gu Gyeonggi-do Yongin-si 16890 South Korea"
    }
  },
  "kimyoungseop_0": {
    "fid": 0,
    "keyId": 914,
    "name": "Kim, Youngseop",
    "pre_name": "kimyoungseop",
    "inst": "Dankook Univ, Elect & Elect Engn, 152 Jukjeon Ro, Yongin 16890, Gyeonggi Do, South Korea",
    "WOS": {
      "inst": "Dankook Univ, Elect & Elect Engn, 152 Jukjeon Ro, Yongin 16890, Gyeonggi Do, South Korea",
      "A_id": [
        "s9505552"
      ],
      "papers": [
        "6294af751649752aa1874751",
        "6294af751649752aa1874773"
      ],
      "oriInst": "Dankook Univ, Elect & Elect Engn, 152 Jukjeon Ro, Yongin 16890, Gyeonggi Do, South Korea"
    }
  },
  "zhangyanning_1": {
    "fid": 0,
    "keyId": 914,
    "name": "Zhang, Yanning",
    "pre_name": "zhangyanning",
    "inst": "National Engineering Laboratory for Integrated Aero-Space-Ground-Ocean Big Data Application Technology School of Cybersecurity Northwestern Polytechnical University Xi'an 710072 China",
    "SCOPUS": {
      "inst": "National Engineering Laboratory for Integrated Aero-Space-Ground-Ocean Big Data Application Technology School of Cybersecurity Northwestern Polytechnical University Xi'an 710072 China",
      "A_id": [
        "56075029000"
      ],
      "papers": [
        "6294af844c7cb9455f86d08a"
      ],
      "oriInst": "National Engineering Laboratory for Integrated Aero-Space-Ground-Ocean Big Data Application Technology School of Cybersecurity Northwestern Polytechnical University Xi'an 710072 China"
    }
  },
  "zhangyanning_0": {
    "fid": 0,
    "keyId": 914,
    "name": "Zhang, Yanning",
    "pre_name": "zhangyanning",
    "inst": "Xidian Univ, Sch Cyber Engn, Xian 710071, Peoples R China",
    "WOS": {
      "inst": "Xidian Univ, Sch Cyber Engn, Xian 710071, Peoples R China",
      "A_id": [
        "ss9683801"
      ],
      "papers": [
        "6294af741649752aa1874701"
      ],
      "oriInst": "Xidian Univ, Sch Cyber Engn, Xian 710071, Peoples R China"
    }
  },
  "dooillchul_1": {
    "fid": 0,
    "keyId": 914,
    "name": "Doo, Illchul",
    "pre_name": "dooillchul",
    "inst": "Artificial Intelligence Education Hankuk University of Foreign Studies Yongin 17035 South Korea",
    "SCOPUS": {
      "inst": "Artificial Intelligence Education Hankuk University of Foreign Studies Yongin 17035 South Korea",
      "A_id": [
        "55990425500"
      ],
      "papers": [
        "6294af844c7cb9455f86d0aa"
      ],
      "oriInst": "Artificial Intelligence Education Hankuk University of Foreign Studies Yongin 17035 South Korea"
    }
  },
  "dooillchul_0": {
    "fid": 0,
    "keyId": 914,
    "name": "Doo, Illchul",
    "pre_name": "dooillchul",
    "inst": "Hankuk Univ Foreign Studies, Artificial Intelligence Educ, Yongin 17035, South Korea",
    "WOS": {
      "inst": "Hankuk Univ Foreign Studies, Artificial Intelligence Educ, Yongin 17035, South Korea",
      "A_id": [
        "ss9683974"
      ],
      "papers": [
        "6294af751649752aa1874736"
      ],
      "oriInst": "Hankuk Univ Foreign Studies, Artificial Intelligence Educ, Yongin 17035, South Korea"
    }
  },
  "aminsaadali_1": {
    "fid": 0,
    "keyId": 914,
    "name": "Amin, Saad Ali",
    "pre_name": "aminsaadali",
    "inst": "College of Engineering and It University of Dubai Dubai CV1 5FB United Arab Emirates",
    "SCOPUS": {
      "inst": "College of Engineering and It University of Dubai Dubai CV1 5FB United Arab Emirates",
      "A_id": [
        "7201845035"
      ],
      "papers": [
        "6294af834c7cb9455f86d060"
      ],
      "oriInst": "College of Engineering and It University of Dubai Dubai CV1 5FB United Arab Emirates"
    }
  },
  "aminsaadali_0": {
    "fid": 0,
    "keyId": 914,
    "name": "Amin, Saad Ali",
    "pre_name": "aminsaadali",
    "inst": "Coventry Univ, Ctr Computat Sci & Math Modelling, Coventry CV1 5FB, W Midlands, England",
    "WOS": {
      "inst": "Coventry Univ, Ctr Computat Sci & Math Modelling, Coventry CV1 5FB, W Midlands, England",
      "A_id": [
        "ss9683847"
      ],
      "papers": [
        "6294af741649752aa1874718"
      ],
      "oriInst": "Coventry Univ, Ctr Computat Sci & Math Modelling, Coventry CV1 5FB, W Midlands, England"
    }
  },
  "ligang_1": {
    "fid": 0,
    "keyId": 914,
    "name": "Li, Gang",
    "pre_name": "ligang",
    "inst": "Centre for Cyber Security Research and Innovation Deakin University Geelong VIC  3216 Australia",
    "SCOPUS": {
      "inst": "Centre for Cyber Security Research and Innovation Deakin University Geelong VIC  3216 Australia",
      "A_id": [
        "56336374700"
      ],
      "papers": [
        "6294af844c7cb9455f86d09e"
      ],
      "oriInst": "Centre for Cyber Security Research and Innovation Deakin University Geelong VIC  3216 Australia"
    }
  },
  "ligang_0": {
    "fid": 0,
    "keyId": 914,
    "name": "Li, Gang",
    "pre_name": "ligang",
    "inst": "Deakin Univ, Ctr Cyber Secur Res & Innovat, Geelong, Vic 3216, Australia",
    "WOS": {
      "inst": "Deakin Univ, Ctr Cyber Secur Res & Innovat, Geelong, Vic 3216, Australia",
      "A_id": [
        "ss9684090"
      ],
      "papers": [
        "6294af751649752aa187475e"
      ],
      "oriInst": "Deakin Univ, Ctr Cyber Secur Res & Innovat, Geelong, Vic 3216, Australia"
    }
  },
  "hindsam_1": {
    "fid": 0,
    "keyId": 914,
    "name": "Hind, Sam",
    "pre_name": "hindsam",
    "inst": "SFB 1187 Media of Cooperation University of Siegen Siegen Germany",
    "SCOPUS": {
      "inst": "SFB 1187 Media of Cooperation University of Siegen Siegen Germany",
      "A_id": [
        "57192439532"
      ],
      "papers": [
        "6294af864c7cb9455f86d125"
      ],
      "oriInst": "SFB 1187 Media of Cooperation University of Siegen Siegen Germany"
    }
  },
  "hindsam_0": {
    "fid": 0,
    "keyId": 914,
    "name": "Hind, Sam",
    "pre_name": "hindsam",
    "inst": "Univ Siegen, SFB Media Of Cooperat 1187, Siegen, Germany",
    "WOS": {
      "inst": "Univ Siegen, SFB Media Of Cooperat 1187, Siegen, Germany",
      "A_id": [
        "ss9683817"
      ],
      "papers": [
        "6294af741649752aa187470b"
      ],
      "oriInst": "Univ Siegen, SFB Media Of Cooperat 1187, Siegen, Germany"
    }
  },
  "zouweiwen_1": {
    "fid": 0,
    "keyId": 914,
    "name": "Zou, Weiwen",
    "pre_name": "zouweiwen",
    "inst": "State Key Laboratory of Advanced Optical Communication Systems and Networks Intelligent Microwave Lightwave Integration Innovation Center (imLic) Department of Electronic Engineering Shanghai Jiao Tong University 800 Dongchuan Road Shanghai 200240 China",
    "SCOPUS": {
      "inst": "State Key Laboratory of Advanced Optical Communication Systems and Networks Intelligent Microwave Lightwave Integration Innovation Center (imLic) Department of Electronic Engineering Shanghai Jiao Tong University 800 Dongchuan Road Shanghai 200240 China",
      "A_id": [
        "15766839600"
      ],
      "papers": [
        "6294af844c7cb9455f86d091"
      ],
      "oriInst": "State Key Laboratory of Advanced Optical Communication Systems and Networks Intelligent Microwave Lightwave Integration Innovation Center (imLic) Department of Electronic Engineering Shanghai Jiao Tong University 800 Dongchuan Road Shanghai 200240 China"
    }
  },
  "zouweiwen_0": {
    "fid": 0,
    "keyId": 914,
    "name": "Zou, Weiwen",
    "pre_name": "zouweiwen",
    "inst": "Chinese Acad Sci, Inst Semicond, Beijing 100083, Peoples R China",
    "WOS": {
      "inst": "Chinese Acad Sci, Inst Semicond, Beijing 100083, Peoples R China",
      "A_id": [
        "ss9684158"
      ],
      "papers": [
        "6294af751649752aa1874779"
      ],
      "oriInst": "Chinese Acad Sci, Inst Semicond, Beijing 100083, Peoples R China"
    }
  },
  "bennamounmohammed_1": {
    "fid": 0,
    "keyId": 914,
    "name": "Bennamoun, Mohammed",
    "pre_name": "bennamounmohammed",
    "inst": "Department of Computer Science and Software Engineering University of Western Australia Crawley WA Australia",
    "SCOPUS": {
      "inst": "Department of Computer Science and Software Engineering University of Western Australia Crawley WA Australia",
      "A_id": [
        "7004376121"
      ],
      "papers": [
        "6294af844c7cb9455f86d090"
      ],
      "oriInst": "Department of Computer Science and Software Engineering University of Western Australia Crawley WA Australia"
    }
  },
  "bennamounmohammed_0": {
    "fid": 0,
    "keyId": 914,
    "name": "Bennamoun, Mohammed",
    "pre_name": "bennamounmohammed",
    "inst": "Univ Western Australia, Dept Comp Sci & Software Engn, Crawley, WA 6009, Australia",
    "WOS": {
      "inst": "Univ Western Australia, Dept Comp Sci & Software Engn, Crawley, WA 6009, Australia",
      "A_id": [
        "s1046569"
      ],
      "papers": [
        "6294af751649752aa187475f"
      ],
      "oriInst": "Univ Western Australia, Dept Comp Sci & Software Engn, Crawley, WA 6009, Australia"
    }
  },
  "perkoroland_1": {
    "fid": 0,
    "keyId": 914,
    "name": "Perko, Roland",
    "pre_name": "perkoroland",
    "inst": "JOANNEUM RESEARCH Forschungsgesellschaft mbH DIGITAL Remote Sensing and Geoinformation Graz 8010 Austria",
    "SCOPUS": {
      "inst": "JOANNEUM RESEARCH Forschungsgesellschaft mbH DIGITAL Remote Sensing and Geoinformation Graz 8010 Austria",
      "A_id": [
        "23397803500"
      ],
      "papers": [
        "6294af844c7cb9455f86d096"
      ],
      "oriInst": "JOANNEUM RESEARCH Forschungsgesellschaft mbH DIGITAL Remote Sensing and Geoinformation Graz 8010 Austria"
    }
  },
  "perkoroland_0": {
    "fid": 0,
    "keyId": 914,
    "name": "Perko, Roland",
    "pre_name": "perkoroland",
    "inst": "Infineon Technol Austria AG, A-9500 Villach, Austria",
    "WOS": {
      "inst": "Infineon Technol Austria AG, A-9500 Villach, Austria",
      "A_id": [
        "ss9683924"
      ],
      "papers": [
        "6294af741649752aa1874729"
      ],
      "oriInst": "Infineon Technol Austria AG, A-9500 Villach, Austria"
    }
  },
  "liw_1": {
    "fid": 0,
    "keyId": 914,
    "name": "Li W.",
    "pre_name": "liw",
    "inst": "Polar Research Institute of China Shanghai 200136 China",
    "SCOPUS": {
      "inst": "Polar Research Institute of China Shanghai 200136 China",
      "A_id": [
        "57283460000"
      ],
      "papers": [
        "6294af844c7cb9455f86d094"
      ],
      "oriInst": "Polar Research Institute of China Shanghai 200136 China"
    }
  },
  "liw_0": {
    "fid": 0,
    "keyId": 914,
    "name": "Li W.",
    "pre_name": "liw",
    "inst": "Information Technology and Cultural Management Institute Hebei Institute of Communications Shijiazhuang 051430 China",
    "SCOPUS": {
      "inst": "Information Technology and Cultural Management Institute Hebei Institute of Communications Shijiazhuang 051430 China",
      "A_id": [
        "57245565200"
      ],
      "papers": [
        "6294af864c7cb9455f86d130"
      ],
      "oriInst": "Information Technology and Cultural Management Institute Hebei Institute of Communications Shijiazhuang 051430 China"
    }
  },
  "veggetejs_1": {
    "fid": 0,
    "keyId": 914,
    "name": "Vegge, Tejs",
    "pre_name": "veggetejs",
    "inst": "Department of Energy Conversion and Storage Anker Engelunds Vej Building 301 Kgs Lyngby DK-2800 Denmark Alistore ERI Amiens France",
    "SCOPUS": {
      "inst": "Department of Energy Conversion and Storage Anker Engelunds Vej Building 301 Kgs Lyngby DK-2800 Denmark Alistore ERI Amiens France",
      "A_id": [
        "7003740838"
      ],
      "papers": [
        "6294af864c7cb9455f86d11f"
      ],
      "oriInst": "Department of Energy Conversion and Storage Anker Engelunds Vej Building 301 Kgs Lyngby DK-2800 Denmark Alistore ERI Amiens France"
    }
  },
  "veggetejs_0": {
    "fid": 0,
    "keyId": 914,
    "name": "Vegge, Tejs",
    "pre_name": "veggetejs",
    "inst": "Helmholtz Inst UIm, Helmholtzstr 11, D-89081 Ulm, Germany",
    "WOS": {
      "inst": "Helmholtz Inst UIm, Helmholtzstr 11, D-89081 Ulm, Germany",
      "A_id": [
        "ss9683937"
      ],
      "papers": [
        "6294af741649752aa187472c"
      ],
      "oriInst": "Helmholtz Inst UIm, Helmholtzstr 11, D-89081 Ulm, Germany"
    }
  },
  "reyescarlal_1": {
    "fid": 0,
    "keyId": 914,
    "name": "Reyes, Carla L.",
    "pre_name": "reyescarlal",
    "inst": "Southern Methodist University Dedman School of Law United States Indiana University Bloomington United States",
    "SCOPUS": {
      "inst": "Southern Methodist University Dedman School of Law United States Indiana University Bloomington United States",
      "A_id": [
        "57044270900"
      ],
      "papers": [
        "6294af864c7cb9455f86d11e"
      ],
      "oriInst": "Southern Methodist University Dedman School of Law United States Indiana University Bloomington United States"
    }
  },
  "reyescarlal_0": {
    "fid": 0,
    "keyId": 914,
    "name": "Reyes, Carla L.",
    "pre_name": "reyescarlal",
    "inst": "Southern Methodist Univ, Dedman Sch Law, Law, Dallas, TX 75275 USA",
    "WOS": {
      "inst": "Southern Methodist Univ, Dedman Sch Law, Law, Dallas, TX 75275 USA",
      "A_id": [
        "ss9683947"
      ],
      "papers": [
        "6294af751649752aa1874730"
      ],
      "oriInst": "Southern Methodist Univ, Dedman Sch Law, Law, Dallas, TX 75275 USA"
    }
  },
  "miclealiviucristian_1": {
    "fid": 0,
    "keyId": 914,
    "name": "Míclea, Liviu Cristian",
    "pre_name": "miclealiviucristian",
    "inst": "Department of Automation Faculty of Automation and Computer Science Technical University Cluj-Napoca 28 Memorandumului Street Cluj-Napoca 400114 Romania",
    "SCOPUS": {
      "inst": "Department of Automation Faculty of Automation and Computer Science Technical University Cluj-Napoca 28 Memorandumului Street Cluj-Napoca 400114 Romania",
      "A_id": [
        "6508329176"
      ],
      "papers": [
        "6294af844c7cb9455f86d08f"
      ],
      "oriInst": "Department of Automation Faculty of Automation and Computer Science Technical University Cluj-Napoca 28 Memorandumului Street Cluj-Napoca 400114 Romania"
    }
  },
  "miclealiviucristian_0": {
    "fid": 0,
    "keyId": 914,
    "name": "Miclea, Liviu-Cristian",
    "pre_name": "miclealiviucristian",
    "inst": "Tech Univ Cluj Napoca, Fac Automat & Comp Sci, Dept Automat, 28 Memorandumului St, Cluj Napoca 400114, Romania",
    "WOS": {
      "inst": "Tech Univ Cluj Napoca, Fac Automat & Comp Sci, Dept Automat, 28 Memorandumului St, Cluj Napoca 400114, Romania",
      "A_id": [
        "ss9683946"
      ],
      "papers": [
        "6294af751649752aa187472f"
      ],
      "oriInst": "Tech Univ Cluj Napoca, Fac Automat & Comp Sci, Dept Automat, 28 Memorandumului St, Cluj Napoca 400114, Romania"
    }
  },
  "lucewu_1": {
    "fid": 0,
    "keyId": 914,
    "name": "Lu, Cewu",
    "pre_name": "lucewu",
    "inst": "Department of Computer Science and Engineering Shanghai Jiao Tong University Shanghai China",
    "SCOPUS": {
      "inst": "Department of Computer Science and Engineering Shanghai Jiao Tong University Shanghai China",
      "A_id": [
        "23035659100"
      ],
      "papers": [
        "6294af834c7cb9455f86d059"
      ],
      "oriInst": "Department of Computer Science and Engineering Shanghai Jiao Tong University Shanghai China"
    }
  },
  "lucewu_0": {
    "fid": 0,
    "keyId": 914,
    "name": "Lu, Cewu",
    "pre_name": "lucewu",
    "inst": "Shanghai Jiao Tong Univ, Dept Comp Sci & Engn, Shanghai 201100, Peoples R China",
    "WOS": {
      "inst": "Shanghai Jiao Tong Univ, Dept Comp Sci & Engn, Shanghai 201100, Peoples R China",
      "A_id": [
        "ss9684073"
      ],
      "papers": [
        "6294af751649752aa187475b"
      ],
      "oriInst": "Shanghai Jiao Tong Univ, Dept Comp Sci & Engn, Shanghai 201100, Peoples R China"
    }
  },
  "vittorinivaleria_1": {
    "fid": 0,
    "keyId": 914,
    "name": "Vittorini, Valeria",
    "pre_name": "vittorinivaleria",
    "inst": "Department of Electrical Engineering and Information Technology University of Naples Federico II 80125 Naples Italy.",
    "SCOPUS": {
      "inst": "Department of Electrical Engineering and Information Technology University of Naples Federico II 80125 Naples Italy.",
      "A_id": [
        "6701381302"
      ],
      "papers": [
        "6294af864c7cb9455f86d116"
      ],
      "oriInst": "Department of Electrical Engineering and Information Technology University of Naples Federico II 80125 Naples Italy."
    }
  },
  "vittorinivaleria_0": {
    "fid": 0,
    "keyId": 914,
    "name": "Vittorini, Valeria",
    "pre_name": "vittorinivaleria",
    "inst": "Univ Napoli Federico II, Dept Elect Engn & Informat Technol, I-80125 Naples, Italy",
    "WOS": {
      "inst": "Univ Napoli Federico II, Dept Elect Engn & Informat Technol, I-80125 Naples, Italy",
      "A_id": [
        "ss9683916"
      ],
      "papers": [
        "6294af741649752aa1874728"
      ],
      "oriInst": "Univ Napoli Federico II, Dept Elect Engn & Informat Technol, I-80125 Naples, Italy"
    }
  },
  "yunaigong_1": {
    "fid": 0,
    "keyId": 914,
    "name": "Yu, Naigong",
    "pre_name": "yunaigong",
    "inst": "Faculty of Information Technology Beijing University of Technology Beijing China Beijing Key Laboratory of Computational Intelligence and Intelligent System Beijing China",
    "SCOPUS": {
      "inst": "Faculty of Information Technology Beijing University of Technology Beijing China Beijing Key Laboratory of Computational Intelligence and Intelligent System Beijing China",
      "A_id": [
        "8267091400"
      ],
      "papers": [
        "6294af864c7cb9455f86d115"
      ],
      "oriInst": "Faculty of Information Technology Beijing University of Technology Beijing China Beijing Key Laboratory of Computational Intelligence and Intelligent System Beijing China"
    }
  },
  "yunaigong_0": {
    "fid": 0,
    "keyId": 914,
    "name": "Yu, Naigong",
    "pre_name": "yunaigong",
    "inst": "Beijing Univ Technol, Fac Informat Technol, Beijing, Peoples R China",
    "WOS": {
      "inst": "Beijing Univ Technol, Fac Informat Technol, Beijing, Peoples R China",
      "A_id": [
        "s1928050"
      ],
      "papers": [
        "6294af741649752aa1874720"
      ],
      "oriInst": "Beijing Univ Technol, Fac Informat Technol, Beijing, Peoples R China"
    }
  },
  "yangqiang_1": {
    "fid": 0,
    "keyId": 914,
    "name": "Yang, Qiang",
    "pre_name": "yangqiang",
    "inst": "WeBank China Hong Kong University of Science and Technology Hong Kong Hong Kong",
    "SCOPUS": {
      "inst": "WeBank China Hong Kong University of Science and Technology Hong Kong Hong Kong",
      "A_id": [
        "57195665626"
      ],
      "papers": [
        "6294af844c7cb9455f86d0b7"
      ],
      "oriInst": "WeBank China Hong Kong University of Science and Technology Hong Kong Hong Kong"
    }
  },
  "yangqiang_0": {
    "fid": 0,
    "keyId": 914,
    "name": "Yang, Qiang",
    "pre_name": "yangqiang",
    "inst": "China UnionPay, Shanghai, Peoples R China",
    "WOS": {
      "inst": "China UnionPay, Shanghai, Peoples R China",
      "A_id": [
        "ss9684103"
      ],
      "papers": [
        "6294af751649752aa1874762"
      ],
      "oriInst": "China UnionPay, Shanghai, Peoples R China"
    }
  },
  "antunesmiguel_1": {
    "fid": 0,
    "keyId": 914,
    "name": "Antunes, Miguel",
    "pre_name": "antunesmiguel",
    "inst": "Department of Electronics University of Alcalá (UAH) Madrid Spain",
    "SCOPUS": {
      "inst": "Department of Electronics University of Alcalá (UAH) Madrid Spain",
      "A_id": [
        "57220578903"
      ],
      "papers": [
        "6294af834c7cb9455f86d084"
      ],
      "oriInst": "Department of Electronics University of Alcalá (UAH) Madrid Spain"
    }
  },
  "antunesmiguel_0": {
    "fid": 0,
    "keyId": 914,
    "name": "Antunes, Miguel",
    "pre_name": "antunesmiguel",
    "inst": "Univ Alcala UAH, Dept Elect, Madrid, Spain",
    "WOS": {
      "inst": "Univ Alcala UAH, Dept Elect, Madrid, Spain",
      "A_id": [
        "ss9683867"
      ],
      "papers": [
        "6294af741649752aa1874721"
      ],
      "oriInst": "Univ Alcala UAH, Dept Elect, Madrid, Spain"
    }
  },
  "huakailung_1": {
    "fid": 0,
    "keyId": 914,
    "name": "Hua, Kailung",
    "pre_name": "huakailung",
    "inst": "Department of Computer Science and Information Engineering National Taiwan University of Science and Technology Taipei 106 Taiwan",
    "SCOPUS": {
      "inst": "Department of Computer Science and Information Engineering National Taiwan University of Science and Technology Taipei 106 Taiwan",
      "A_id": [
        "55223901500"
      ],
      "papers": [
        "6294af834c7cb9455f86d082"
      ],
      "oriInst": "Department of Computer Science and Information Engineering National Taiwan University of Science and Technology Taipei 106 Taiwan"
    }
  },
  "huakailung_0": {
    "fid": 0,
    "keyId": 914,
    "name": "Hua, Kai-Lung",
    "pre_name": "huakailung",
    "inst": "Natl Taiwan Univ Sci & Technol, Dept Ind Management, Taipei 106, Taiwan",
    "WOS": {
      "inst": "Natl Taiwan Univ Sci & Technol, Dept Ind Management, Taipei 106, Taiwan",
      "A_id": [
        "s2775727"
      ],
      "papers": [
        "6294af741649752aa18746e8"
      ],
      "oriInst": "Natl Taiwan Univ Sci & Technol, Dept Ind Management, Taipei 106, Taiwan"
    }
  },
  "dudehui_1": {
    "fid": 0,
    "keyId": 914,
    "name": "Du, Dehui",
    "pre_name": "dudehui",
    "inst": "School of Software and Engineering East China Normal University Shanghai 200062 China Shanghai Key Laboratory of Trustworthy Computing East China Normal University Shanghai 200062 China MOE International Joint Lab of Trustworthy Software East China Normal University Shanghai 200062 China",
    "SCOPUS": {
      "inst": "School of Software and Engineering East China Normal University Shanghai 200062 China Shanghai Key Laboratory of Trustworthy Computing East China Normal University Shanghai 200062 China MOE International Joint Lab of Trustworthy Software East China Normal University Shanghai 200062 China",
      "A_id": [
        "14044898400"
      ],
      "papers": [
        "6294af844c7cb9455f86d0a8"
      ],
      "oriInst": "School of Software and Engineering East China Normal University Shanghai 200062 China Shanghai Key Laboratory of Trustworthy Computing East China Normal University Shanghai 200062 China MOE International Joint Lab of Trustworthy Software East China Normal University Shanghai 200062 China"
    }
  },
  "dudehui_0": {
    "fid": 0,
    "keyId": 914,
    "name": "Du, Dehui",
    "pre_name": "dudehui",
    "inst": "East China Normal Univ, Sch Software & Engn, Shanghai 200062, Peoples R China",
    "WOS": {
      "inst": "East China Normal Univ, Sch Software & Engn, Shanghai 200062, Peoples R China",
      "A_id": [
        "ss9496830"
      ],
      "papers": [
        "6294af741649752aa18746eb"
      ],
      "oriInst": "East China Normal Univ, Sch Software & Engn, Shanghai 200062, Peoples R China"
    }
  },
  "chokyungeun_1": {
    "fid": 0,
    "keyId": 914,
    "name": "Cho, Kyungeun",
    "pre_name": "chokyungeun",
    "inst": "Department of Multimedia Engineering Dongguk University-Seoul 30 Pildong-ro 1-gil Jung-gu Seoul 04620 South Korea",
    "SCOPUS": {
      "inst": "Department of Multimedia Engineering Dongguk University-Seoul 30 Pildong-ro 1-gil Jung-gu Seoul 04620 South Korea",
      "A_id": [
        "14833735900"
      ],
      "papers": [
        "6294af834c7cb9455f86d05f"
      ],
      "oriInst": "Department of Multimedia Engineering Dongguk University-Seoul 30 Pildong-ro 1-gil Jung-gu Seoul 04620 South Korea"
    }
  },
  "chokyungeun_0": {
    "fid": 0,
    "keyId": 914,
    "name": "Cho, Kyungeun",
    "pre_name": "chokyungeun",
    "inst": "Dongguk Univ, Dept Multimedia Engn, 30 Pildong Ro 1 Gil, Seoul 04620, South Korea",
    "WOS": {
      "inst": "Dongguk Univ, Dept Multimedia Engn, 30 Pildong Ro 1 Gil, Seoul 04620, South Korea",
      "A_id": [
        "ss9683884"
      ],
      "papers": [
        "6294af741649752aa1874725"
      ],
      "oriInst": "Dongguk Univ, Dept Multimedia Engn, 30 Pildong Ro 1 Gil, Seoul 04620, South Korea"
    }
  },
  "leekyujin_1": {
    "fid": 0,
    "keyId": 914,
    "name": "Lee, Kyujin",
    "pre_name": "leekyujin",
    "inst": "Department of Electronic Engineering Semyung University 65 Semyung-ro Chungcheongbuk-do Jecheon-si 27136 South Korea",
    "SCOPUS": {
      "inst": "Department of Electronic Engineering Semyung University 65 Semyung-ro Chungcheongbuk-do Jecheon-si 27136 South Korea",
      "A_id": [
        "13410076000"
      ],
      "papers": [
        "6294af834c7cb9455f86d05e"
      ],
      "oriInst": "Department of Electronic Engineering Semyung University 65 Semyung-ro Chungcheongbuk-do Jecheon-si 27136 South Korea"
    }
  },
  "leekyujin_0": {
    "fid": 0,
    "keyId": 914,
    "name": "Lee, Kyujin",
    "pre_name": "leekyujin",
    "inst": "Semyung Univ, Dept Elect Engn, 65 Semyung Ro, Jecheon Si 27136, Chungcheongbuk, South Korea",
    "WOS": {
      "inst": "Semyung Univ, Dept Elect Engn, 65 Semyung Ro, Jecheon Si 27136, Chungcheongbuk, South Korea",
      "A_id": [
        "ss9683842"
      ],
      "papers": [
        "6294af741649752aa1874716"
      ],
      "oriInst": "Semyung Univ, Dept Elect Engn, 65 Semyung Ro, Jecheon Si 27136, Chungcheongbuk, South Korea"
    }
  },
  "choromanskaanna_1": {
    "fid": 0,
    "keyId": 914,
    "name": "Choromanska, Anna",
    "pre_name": "choromanskaanna",
    "inst": "Learning Systems Laboratory Department of Electrical and Computer Engineering New York University 5 MetroTech Center Brooklyn NY  11201 United States",
    "SCOPUS": {
      "inst": "Learning Systems Laboratory Department of Electrical and Computer Engineering New York University 5 MetroTech Center Brooklyn NY  11201 United States",
      "A_id": [
        "36022226300"
      ],
      "papers": [
        "6294af834c7cb9455f86d057"
      ],
      "oriInst": "Learning Systems Laboratory Department of Electrical and Computer Engineering New York University 5 MetroTech Center Brooklyn NY  11201 United States"
    }
  },
  "choromanskaanna_0": {
    "fid": 0,
    "keyId": 914,
    "name": "Choromanska, Anna",
    "pre_name": "choromanskaanna",
    "inst": "NYU, Dept Elect & Comp Engn, Learning Syst Lab, 5 MetroTech Ctr, Brooklyn, NY 11201 USA",
    "WOS": {
      "inst": "NYU, Dept Elect & Comp Engn, Learning Syst Lab, 5 MetroTech Ctr, Brooklyn, NY 11201 USA",
      "A_id": [
        "ss9683804"
      ],
      "papers": [
        "6294af741649752aa1874703"
      ],
      "oriInst": "NYU, Dept Elect & Comp Engn, Learning Syst Lab, 5 MetroTech Ctr, Brooklyn, NY 11201 USA"
    }
  },
  "peetasrinivas_1": {
    "fid": 0,
    "keyId": 914,
    "name": "Peeta, Srinivas",
    "pre_name": "peetasrinivas",
    "inst": "School of Civil and Environmental Engineering Georgia Institue of Technology Atlanta GA United States",
    "SCOPUS": {
      "inst": "School of Civil and Environmental Engineering Georgia Institue of Technology Atlanta GA United States",
      "A_id": [
        "6701616998"
      ],
      "papers": [
        "6294af834c7cb9455f86d081"
      ],
      "oriInst": "School of Civil and Environmental Engineering Georgia Institue of Technology Atlanta GA United States"
    }
  },
  "peetasrinivas_0": {
    "fid": 0,
    "keyId": 914,
    "name": "Peeta, Srinivas",
    "pre_name": "peetasrinivas",
    "inst": "Georgia Inst Technol, Sch Civil & Environm Engn, Atlanta, GA 30332 USA",
    "WOS": {
      "inst": "Georgia Inst Technol, Sch Civil & Environm Engn, Atlanta, GA 30332 USA",
      "A_id": [
        "s2089287"
      ],
      "papers": [
        "6294af751649752aa187474a"
      ],
      "oriInst": "Georgia Inst Technol, Sch Civil & Environm Engn, Atlanta, GA 30332 USA"
    }
  },
  "ozolskaspars_1": {
    "fid": 0,
    "keyId": 914,
    "name": "Ozols, Kaspars",
    "pre_name": "ozolskaspars",
    "inst": "Institute of Electronics and Computer Science Dzerbenes Str.14 Riga LV-1006 Latvia",
    "SCOPUS": {
      "inst": "Institute of Electronics and Computer Science Dzerbenes Str.14 Riga LV-1006 Latvia",
      "A_id": [
        "57208987064"
      ],
      "papers": [
        "6294af834c7cb9455f86d05d"
      ],
      "oriInst": "Institute of Electronics and Computer Science Dzerbenes Str.14 Riga LV-1006 Latvia"
    }
  },
  "ozolskaspars_0": {
    "fid": 0,
    "keyId": 914,
    "name": "Ozols, Kaspars",
    "pre_name": "ozolskaspars",
    "inst": "Inst Elect & Comp Sci, Dzerbenes Str 14, LV-1006 Riga, Latvia",
    "WOS": {
      "inst": "Inst Elect & Comp Sci, Dzerbenes Str 14, LV-1006 Riga, Latvia",
      "A_id": [
        "ss9684096"
      ],
      "papers": [
        "6294af751649752aa1874760"
      ],
      "oriInst": "Inst Elect & Comp Sci, Dzerbenes Str 14, LV-1006 Riga, Latvia"
    }
  },
  "tianzengshan_1": {
    "fid": 0,
    "keyId": 914,
    "name": "Tian, Zengshan",
    "pre_name": "tianzengshan",
    "inst": "School of Communication and Information Engineering Chongqing University of Posts and Telecommunications Chongqing China",
    "SCOPUS": {
      "inst": "School of Communication and Information Engineering Chongqing University of Posts and Telecommunications Chongqing China",
      "A_id": [
        "55506175400"
      ],
      "papers": [
        "6294af834c7cb9455f86d04c"
      ],
      "oriInst": "School of Communication and Information Engineering Chongqing University of Posts and Telecommunications Chongqing China"
    }
  },
  "tianzengshan_0": {
    "fid": 0,
    "keyId": 914,
    "name": "Tian, Zengshan",
    "pre_name": "tianzengshan",
    "inst": "Chongqing Univ Posts & Telecommun, Sch Commun & Informat Engn, Chongqing, Peoples R China",
    "WOS": {
      "inst": "Chongqing Univ Posts & Telecommun, Sch Commun & Informat Engn, Chongqing, Peoples R China",
      "A_id": [
        "ss9684146"
      ],
      "papers": [
        "6294af751649752aa1874775"
      ],
      "oriInst": "Chongqing Univ Posts & Telecommun, Sch Commun & Informat Engn, Chongqing, Peoples R China"
    }
  },
  "yinzhaozheng_1": {
    "fid": 0,
    "keyId": 914,
    "name": "Yin, Zhaozheng",
    "pre_name": "yinzhaozheng",
    "inst": "Department of Biomedical Informatics the Department of Computer Science and the AI Institute Stony Brook University Stony Brook NY 11794 USA.",
    "SCOPUS": {
      "inst": "Department of Biomedical Informatics the Department of Computer Science and the AI Institute Stony Brook University Stony Brook NY 11794 USA.",
      "A_id": [
        "36351279000"
      ],
      "papers": [
        "6294af834c7cb9455f86d079"
      ],
      "oriInst": "Department of Biomedical Informatics the Department of Computer Science and the AI Institute Stony Brook University Stony Brook NY 11794 USA."
    }
  },
  "yinzhaozheng_0": {
    "fid": 0,
    "keyId": 914,
    "name": "Yin, Zhaozheng",
    "pre_name": "yinzhaozheng",
    "inst": "SUNY Stony Brook, Dept Biomed Informat, Dept Comp Sci, Stony Brook, NY 11794 USA",
    "WOS": {
      "inst": "SUNY Stony Brook, Dept Biomed Informat, Dept Comp Sci, Stony Brook, NY 11794 USA",
      "A_id": [
        "s8597383"
      ],
      "papers": [
        "6294af751649752aa1874755"
      ],
      "oriInst": "SUNY Stony Brook, Dept Biomed Informat, Dept Comp Sci, Stony Brook, NY 11794 USA"
    }
  },
  "namhaewoon_1": {
    "fid": 0,
    "keyId": 914,
    "name": "Nam, Haewoon",
    "pre_name": "namhaewoon",
    "inst": "Division of Electrical Engineering Hanyang University Ansan 15588 South Korea",
    "SCOPUS": {
      "inst": "Division of Electrical Engineering Hanyang University Ansan 15588 South Korea",
      "A_id": [
        "15078425500"
      ],
      "papers": [
        "6294af834c7cb9455f86d078"
      ],
      "oriInst": "Division of Electrical Engineering Hanyang University Ansan 15588 South Korea"
    }
  },
  "namhaewoon_0": {
    "fid": 0,
    "keyId": 914,
    "name": "Nam, Haewoon",
    "pre_name": "namhaewoon",
    "inst": "Hanyang Univ, Div Elect Engn, Ansan 15588, South Korea",
    "WOS": {
      "inst": "Hanyang Univ, Div Elect Engn, Ansan 15588, South Korea",
      "A_id": [
        "s6890627"
      ],
      "papers": [
        "6294af751649752aa1874744"
      ],
      "oriInst": "Hanyang Univ, Div Elect Engn, Ansan 15588, South Korea"
    }
  },
  "kimsangho_1": {
    "fid": 0,
    "keyId": 914,
    "name": "Kim, Sang-ho",
    "pre_name": "kimsangho",
    "inst": "Department of Industrial Engineering Kumoh National Institute of Technology South Korea",
    "SCOPUS": {
      "inst": "Department of Industrial Engineering Kumoh National Institute of Technology South Korea",
      "A_id": [
        "57189310155"
      ],
      "papers": [
        "6294af834c7cb9455f86d075"
      ],
      "oriInst": "Department of Industrial Engineering Kumoh National Institute of Technology South Korea"
    }
  },
  "kimsangho_0": {
    "fid": 0,
    "keyId": 914,
    "name": "Kim, Sang-Ho",
    "pre_name": "kimsangho",
    "inst": "Kumoh Natl Inst Technol, Dept Ind Engn, 61 Daehak Ro, Gumi 39177, Gyeongbuk, South Korea",
    "WOS": {
      "inst": "Kumoh Natl Inst Technol, Dept Ind Engn, 61 Daehak Ro, Gumi 39177, Gyeongbuk, South Korea",
      "A_id": [
        "ss9683844"
      ],
      "papers": [
        "6294af741649752aa1874717"
      ],
      "oriInst": "Kumoh Natl Inst Technol, Dept Ind Engn, 61 Daehak Ro, Gumi 39177, Gyeongbuk, South Korea"
    }
  },
  "lihao_1": {
    "fid": 0,
    "keyId": 914,
    "name": "Li, Hao",
    "pre_name": "lihao",
    "inst": "Science and Technology on Communication Networks Laboratory Shijiazhuang 050081 China",
    "SCOPUS": {
      "inst": "Science and Technology on Communication Networks Laboratory Shijiazhuang 050081 China",
      "A_id": [
        "57191614101"
      ],
      "papers": [
        "6294af834c7cb9455f86d055"
      ],
      "oriInst": "Science and Technology on Communication Networks Laboratory Shijiazhuang 050081 China"
    }
  },
  "lihao_0": {
    "fid": 0,
    "keyId": 914,
    "name": "Li, Hao",
    "pre_name": "lihao",
    "inst": "Sci & Technol Commun Networks Lab, Shijiazhuang 050081, Hebei, Peoples R China",
    "WOS": {
      "inst": "Sci & Technol Commun Networks Lab, Shijiazhuang 050081, Hebei, Peoples R China",
      "A_id": [
        "ss9538388"
      ],
      "papers": [
        "6294af751649752aa1874766"
      ],
      "oriInst": "Sci & Technol Commun Networks Lab, Shijiazhuang 050081, Hebei, Peoples R China"
    }
  },
  "meekerwilliamq_1": {
    "fid": 0,
    "keyId": 914,
    "name": "Meeker, William Q.",
    "pre_name": "meekerwilliamq",
    "inst": "Department of Statistics Iowa State University Ames IA United States",
    "SCOPUS": {
      "inst": "Department of Statistics Iowa State University Ames IA United States",
      "A_id": [
        "7006982489"
      ],
      "papers": [
        "6294af834c7cb9455f86d06d"
      ],
      "oriInst": "Department of Statistics Iowa State University Ames IA United States"
    }
  },
  "meekerwilliamq_0": {
    "fid": 0,
    "keyId": 914,
    "name": "Meeker, William Q.",
    "pre_name": "meekerwilliamq",
    "inst": "Iowa State Univ, Dept Stat, Ames, IA USA",
    "WOS": {
      "inst": "Iowa State Univ, Dept Stat, Ames, IA USA",
      "A_id": [
        "s2590082"
      ],
      "papers": [
        "6294af741649752aa1874705"
      ],
      "oriInst": "Iowa State Univ, Dept Stat, Ames, IA USA"
    }
  },
  "zeleznikowjohn_1": {
    "fid": 0,
    "keyId": 914,
    "name": "Zeleznikow, John",
    "pre_name": "zeleznikowjohn",
    "inst": "La Trobe University Melbourne Australia",
    "SCOPUS": {
      "inst": "La Trobe University Melbourne Australia",
      "A_id": [
        "6701828144"
      ],
      "papers": [
        "6294af834c7cb9455f86d06a"
      ],
      "oriInst": "La Trobe University Melbourne Australia"
    }
  },
  "zeleznikowjohn_0": {
    "fid": 0,
    "keyId": 914,
    "name": "Zeleznikow, John",
    "pre_name": "zeleznikowjohn",
    "inst": "La Trobe Univ, Melbourne, Vic, Australia",
    "WOS": {
      "inst": "La Trobe Univ, Melbourne, Vic, Australia",
      "A_id": [
        "ss9683833"
      ],
      "papers": [
        "6294af741649752aa1874712"
      ],
      "oriInst": "La Trobe Univ, Melbourne, Vic, Australia"
    }
  },
  "qureshimuhammadaasim_1": {
    "fid": 0,
    "keyId": 914,
    "name": "Qureshi, Muhammad Aasim",
    "pre_name": "qureshimuhammadaasim",
    "inst": "Department Of Computer Sciences Bahria University Lahore Campus Lahore 54000 Pakistan",
    "SCOPUS": {
      "inst": "Department Of Computer Sciences Bahria University Lahore Campus Lahore 54000 Pakistan",
      "A_id": [
        "36053793400"
      ],
      "papers": [
        "6294af834c7cb9455f86d069"
      ],
      "oriInst": "Department Of Computer Sciences Bahria University Lahore Campus Lahore 54000 Pakistan"
    }
  },
  "qureshimuhammadaasim_0": {
    "fid": 0,
    "keyId": 914,
    "name": "Qureshi, Muhammad Aasim",
    "pre_name": "qureshimuhammadaasim",
    "inst": "Bahria Univ, Dept Comp Sci, Lahore Campus, Lahore 54000, Pakistan",
    "WOS": {
      "inst": "Bahria Univ, Dept Comp Sci, Lahore Campus, Lahore 54000, Pakistan",
      "A_id": [
        "s9308848"
      ],
      "papers": [
        "6294af741649752aa18746ee"
      ],
      "oriInst": "Bahria Univ, Dept Comp Sci, Lahore Campus, Lahore 54000, Pakistan"
    }
  }
}